youtube_dl_gui/GUI/AboutDialog.py
youtube_dl_gui/GUI/BatchAddUrls.py
youtube_dl_gui/GUI/LicenseDialog.py
youtube_dl_gui/GUI/__init__.py
youtube_dl_gui/Threads/Download.py
youtube_dl_gui/Threads/PostProcessor.py
youtube_dl_gui/Threads/__init__.py
youtube_dl_gui/UI/__init__.py
youtube_dl_gui/UI/images/icon.ico
youtube_dl_gui/UI/images/icon.png
youtube_dl_gui/UI/images/logo.png
youtube_dl_gui/UI/resources/AboutDialog.ui
youtube_dl_gui/UI/resources/BatchAddUrls.ui
youtube_dl_gui/UI/resources/LicenseDialog.ui
youtube_dl_gui/UI/resources/converted_icon.ico
youtube_dl_gui/UI/resources/gui.ui
youtube_dl_gui/UI/resources/gui_qt-designer.ui
youtube_dl_gui/UI/resources/icon.ico
youtube_dl_gui/UI/resources/icon.png
youtube_dl_gui/UI/resources/inno_script.iss
youtube_dl_gui/UI/resources/logo.png
youtube_dl_gui/UI/resources/pause-icon.svg
youtube_dl_gui/UI/resources/resource.qrc
youtube_dl_gui/UI/resources/resume-icon.svg
youtube_dl_gui/UI/resources/stop-icon.png
youtube_dl_gui/__init__.py
youtube_dl_gui/generate_resources.py
youtube_dl_gui/main.py
youtube_dl_gui-1.0.4.dist-info/entry_points.txt
youtube_dl_gui-1.0.4.dist-info/LICENSE
youtube_dl_gui-1.0.4.dist-info/WHEEL
youtube_dl_gui-1.0.4.dist-info/METADATA
youtube_dl_gui-1.0.4.dist-info/RECORD
